s5/__init__.py
s5/init.py
s5/jax_compat.py
s5/s5_model.py
s5_pytorch-0.1.7.dist-info/LICENSE
s5_pytorch-0.1.7.dist-info/METADATA
s5_pytorch-0.1.7.dist-info/WHEEL
s5_pytorch-0.1.7.dist-info/top_level.txt
s5_pytorch-0.1.7.dist-info/RECORD
