Metadata-Version: 2.1
Name: s5-pytorch
Version: 0.1.7
Summary: S5 - Simplified State Space Layers for Sequence Modeling - Pytorch
Home-page: https://github.com/lucidrains/audiolm-pytorch
Author: Ferris Kwaijtaal
Author-email: ferris+gh@devdroplets.com
License: MIT
Keywords: artificial intelligence,deep learning,transformers,attention mechanism,audio generation
Classifier: Development Status :: 4 - Beta
Classifier: Intended Audience :: Developers
Classifier: Topic :: Scientific/Engineering :: Artificial Intelligence
Classifier: License :: OSI Approved :: MIT License
Classifier: Programming Language :: Python :: 3.10
License-File: LICENSE
Requires-Dist: einops (>=0.6)
Requires-Dist: scipy
Requires-Dist: torch (>=1.13)
Requires-Dist: jax
